README.md
setup.py
marketpy/__init__.py
marketpy/metrics.py
marketpy/preprocessing.py
marketpy.egg-info/PKG-INFO
marketpy.egg-info/SOURCES.txt
marketpy.egg-info/dependency_links.txt
marketpy.egg-info/not-zip-safe
marketpy.egg-info/requires.txt
marketpy.egg-info/top_level.txt