Metadata-Version: 1.0
Name: marketpy
Version: 0.1
Summary: Python library for financial modeling
Home-page: http://github.com/storborg/funniest
Author: Olaf Skrabacz
Author-email: olafsk123@gmail.com
License: MIT
Platform: UNKNOWN
